mfd_dcb/__init__.py
mfd_dcb/const.py
mfd_dcb/data_structures.py
mfd_dcb/dcbnl_wrapper.py
mfd_dcb/dcbtool_wrapper.py
mfd_dcb/enums.py
mfd_dcb/exceptions.py
mfd_dcb/freebsd.py
mfd_dcb/linux.py
mfd_dcb/mfd_dcb.py
mfd_dcb/windows.py
mfd_dcb-1.18.0.dist-info/licenses/AUTHORS.md
mfd_dcb-1.18.0.dist-info/licenses/LICENSE.md
mfd_dcb-1.18.0.dist-info/METADATA
mfd_dcb-1.18.0.dist-info/WHEEL
mfd_dcb-1.18.0.dist-info/top_level.txt
mfd_dcb-1.18.0.dist-info/RECORD
