Metadata-Version: 2.4
Name: mfd-dcb
Version: 1.18.0
Summary: A Python module providing cross-platform Data Center Bridging (DCB) configuration and management APIs for Windows, Linux, and FreeBSD systems.
Project-URL: Homepage, https://github.com/intel/mfd
Project-URL: Repository, https://github.com/intel/mfd-dcb
Project-URL: Issues, https://github.com/intel/mfd-dcb/issues
Project-URL: Changelog, https://github.com/intel/mfd-dcb/blob/main/CHANGELOG.md
Requires-Python: <3.14,>=3.10
License-File: LICENSE.md
License-File: AUTHORS.md
Requires-Dist: mfd-common-libs>=1.11.0
Requires-Dist: mfd-ethtool>=3.14.0
Requires-Dist: mfd-const>=0.23.0
Requires-Dist: mfd-typing>=1.23.0
Requires-Dist: mfd-sysctl<2,>=1.6.0
Dynamic: license-file
